motulator/__init__.py
motulator/common/__init__.py
motulator/common/control/__init__.py
motulator/common/control/_base.py
motulator/common/control/_controllers.py
motulator/common/control/_pwm.py
motulator/common/model/__init__.py
motulator/common/model/_base.py
motulator/common/model/_converter.py
motulator/common/model/_pwm.py
motulator/common/model/_simulation.py
motulator/common/utils/__init__.py
motulator/common/utils/_plotting.py
motulator/common/utils/_utils.py
motulator/drive/__init__.py
motulator/drive/control/__init__.py
motulator/drive/control/_base.py
motulator/drive/control/_common.py
motulator/drive/control/_im_current_vector.py
motulator/drive/control/_im_flux_vector.py
motulator/drive/control/_im_observers.py
motulator/drive/control/_sm_current_vector.py
motulator/drive/control/_sm_flux_vector.py
motulator/drive/control/_sm_observers.py
motulator/drive/control/_sm_reference_gen.py
motulator/drive/control/_sm_signal_inj.py
motulator/drive/control/im.py
motulator/drive/control/sm.py
motulator/drive/model/__init__.py
motulator/drive/model/_drive.py
motulator/drive/model/_lc_filter.py
motulator/drive/model/_machine.py
motulator/drive/model/_mechanics.py
motulator/drive/utils/__init__.py
motulator/drive/utils/_parameters.py
motulator/drive/utils/_plots.py
motulator/drive/utils/_sm_control_loci.py
motulator/drive/utils/_sm_flux_maps.py
motulator/drive/utils/_sm_plot_control_loci.py
motulator/drive/utils/_sm_plot_flux_maps.py
motulator/grid/__init__.py
motulator/grid/control/__init__.py
motulator/grid/control/_base.py
motulator/grid/control/_common.py
motulator/grid/control/_gfl_current_vector.py
motulator/grid/control/_gfm_observer.py
motulator/grid/control/_gfm_psc.py
motulator/grid/model/__init__.py
motulator/grid/model/_ac_filter.py
motulator/grid/model/_ac_source.py
motulator/grid/model/_converter_system.py
motulator/grid/utils/__init__.py
motulator/grid/utils/_plots.py
motulator-0.7.3.dist-info/METADATA
motulator-0.7.3.dist-info/WHEEL
motulator-0.7.3.dist-info/licenses/LICENSE
motulator-0.7.3.dist-info/RECORD
