Metadata-Version: 2.4
Name: motulator
Version: 0.7.3
Summary: Motor Drive and Grid Converter Simulator in Python
Project-URL: Homepage, https://github.com/Aalto-Electric-Drives/motulator
Project-URL: Documentation, https://Aalto-Electric-Drives.github.io/motulator/
Author-email: Marko Hinkkanen <marko.hinkkanen@aalto.fi>
License-Expression: MIT
License-File: LICENSE
Keywords: control,converter,electric,grid,inverter,machine,motor,power,simulation
Classifier: License :: OSI Approved :: MIT License
Classifier: Operating System :: OS Independent
Classifier: Programming Language :: Python
Requires-Python: >=3.12
Requires-Dist: matplotlib
Requires-Dist: numpy
Requires-Dist: scipy
Requires-Dist: tqdm
Provides-Extra: dev
Requires-Dist: ipykernel; extra == 'dev'
Requires-Dist: pip-audit; extra == 'dev'
Requires-Dist: pre-commit; extra == 'dev'
Requires-Dist: pyright; extra == 'dev'
Requires-Dist: ruff; extra == 'dev'
Requires-Dist: toml; extra == 'dev'
Provides-Extra: doc
Requires-Dist: esbonio; extra == 'doc'
Requires-Dist: myst-parser; extra == 'doc'
Requires-Dist: numpydoc; extra == 'doc'
Requires-Dist: sphinx; extra == 'doc'
Requires-Dist: sphinx-autoapi; extra == 'doc'
Requires-Dist: sphinx-book-theme; extra == 'doc'
Requires-Dist: sphinx-copybutton; extra == 'doc'
Requires-Dist: sphinx-gallery; extra == 'doc'
Requires-Dist: sphinxcontrib-bibtex; extra == 'doc'
